atprogram/__init__.py
atprogram/atprogram.py
pydgilib/__init__.py
pydgilib/dgilib.py
pydgilib/dgilib_auxiliary.py
pydgilib/dgilib_config.py
pydgilib/dgilib_discovery.py
pydgilib/dgilib_exceptions.py
pydgilib/dgilib_housekeeping.py
pydgilib/dgilib_interface_communication.py
pydgilib_extra/__init__.py
pydgilib_extra/dgilib_calculations.py
pydgilib_extra/dgilib_data.py
pydgilib_extra/dgilib_extra.py
pydgilib_extra/dgilib_extra_config.py
pydgilib_extra/dgilib_extra_exceptions.py
pydgilib_extra/dgilib_interface.py
pydgilib_extra/dgilib_interface_gpio.py
pydgilib_extra/dgilib_interface_power.py
pydgilib_extra/dgilib_logger.py
pydgilib_extra/dgilib_plot.py
pydgilib-0.2.3.dist-info/LICENCE
pydgilib-0.2.3.dist-info/METADATA
pydgilib-0.2.3.dist-info/WHEEL
pydgilib-0.2.3.dist-info/dependency_links.txt
pydgilib-0.2.3.dist-info/top_level.txt
pydgilib-0.2.3.dist-info/RECORD
