Metadata-Version: 2.1
Name: pydgilib
Version: 0.2.3
Summary: This module provides Python bindings for DGILib.
Home-page: https://github.com/EWouters/pydgilib
Author: Erik Wouters
Author-email: ehwo@kth.se
License: BSD-3-Clause
Platform: UNKNOWN
Provides-Extra: docs
Requires-Dist: Sphinx ; extra == 'docs'
Requires-Dist: sphinx-rtd-theme ; extra == 'docs'
Provides-Extra: test
Requires-Dist: pytest-runner ; extra == 'test'
Requires-Dist: pytest-benchmark ; extra == 'test'
Requires-Dist: pytest-cov ; extra == 'test'
